sorl_thumbnail_async-0.6.0.dist-info/DESCRIPTION.rst
sorl_thumbnail_async-0.6.0.dist-info/METADATA
sorl_thumbnail_async-0.6.0.dist-info/metadata.json
sorl_thumbnail_async-0.6.0.dist-info/RECORD
sorl_thumbnail_async-0.6.0.dist-info/top_level.txt
sorl_thumbnail_async-0.6.0.dist-info/WHEEL
thumbnail/__init__.py
thumbnail/backend.py
thumbnail/models.py
thumbnail/tasks.py
thumbnail/utils.py
thumbnail/conf/__init__.py
thumbnail/conf/settings.py
thumbnail/templatetags/__init__.py
thumbnail/templatetags/thumbnail_tags.py
