Metadata-Version: 2.0
Name: sorl-thumbnail-async
Version: 0.6.0
Summary: Asynchronous thumbnailing app in django with remote storages like S3
Home-page: https://github.com/chhantyal/sorl-thumbnail-async
Author: Nar Kumar Chhantyal
Author-email: nkchhantyal@gmail.com
License: UNKNOWN
Platform: UNKNOWN
Classifier: Intended Audience :: Developers
Classifier: Operating System :: OS Independent
Classifier: Programming Language :: Python
Classifier: Programming Language :: Python :: 2.6
Classifier: Programming Language :: Python :: 2.7
Classifier: Programming Language :: Python :: 3
Classifier: Programming Language :: Python :: 3.3
Classifier: Programming Language :: Python :: 3.4
Classifier: Topic :: Software Development :: Libraries :: Python Modules
Classifier: Framework :: Django
Classifier: Environment :: Web Environment
